{"_09532ad3-e571-4214-b580-7bebf4bb68b1":{"next":[{"name":null,"id":"_3e5ac6ed-88d6-4f82-a647-6b253b80b004"}],"finalPhrase":{"objectDeterminant":"false","subject":null,"interrogative":"false","verb":null,"complement":null,"objectPlural":"false","existActions":"false","object":null},"name":"Task 4","id":"_09532ad3-e571-4214-b580-7bebf4bb68b1","type":"task","actions":null,"lane":null,"finalSentence":"Task 4."},"_3e5ac6ed-88d6-4f82-a647-6b253b80b004":{"next":[],"finalPhrase":{"objectDeterminant":"true","subject":null,"interrogative":"false","verb":"end","complement":null,"objectPlural":"false","existActions":"true","object":"event 3"},"name":"End Event 3","id":"_3e5ac6ed-88d6-4f82-a647-6b253b80b004","type":"endEvent","actions":{"predPoS":"NN","objW":"event 3","predL":"end","objL":"event","objMSD":"pos=noun|type=common|num=singular","predW":"end","predF":"end","objF":"event","predMSD":"pos=noun|type=common|num=singular","objPoS":"NN"},"lane":null,"finalSentence":"The event 3 is ended."},"_1ffaa550-3225-4c6a-a391-3aaf224723af":{"next":[{"name":null,"id":"_09532ad3-e571-4214-b580-7bebf4bb68b1"}],"finalPhrase":{"objectDeterminant":"true","subject":null,"interrogative":"false","verb":"start","complement":null,"objectPlural":"false","existActions":"true","object":"event 3"},"name":"Start Event 3","id":"_1ffaa550-3225-4c6a-a391-3aaf224723af","type":"startEvent","actions":{"predPoS":"NN","objW":"event 3","predL":"start","objL":"event","objMSD":"pos=noun|type=common|num=singular","predW":"start","predF":"start","objF":"event","predMSD":"pos=noun|type=common|num=singular","objPoS":"NN"},"lane":null,"finalSentence":"The event 3 is started."}}