{"invoice_approved":{"next":[{"name":"yes","id":"prepareBankTransfer"},{"name":"no","id":"reviewInvoice"}],"finalPhrase":{"objectDeterminant":"true","subject":null,"interrogative":"true","verb":"invoice","complement":null,"objectPlural":"false","existActions":"true","object":"approved"},"name":"Invoice approved?","id":"invoice_approved","type":"exclusiveGateway","actions":{"predPoS":"NN","objW":"approved","predL":"invoice","objL":"approve","objMSD":"pos=verb|vform=past","predW":"invoice","predF":"invoice","objF":"approved","predMSD":"pos=noun|type=common|num=singular","objPoS":"VBD"},"lane":null,"finalSentence":"Does invoice the approved?"},"approveInvoice":{"next":[{"name":null,"id":"invoice_approved"}],"finalPhrase":{"objectDeterminant":"true","subject":null,"interrogative":"false","verb":"approve","complement":null,"objectPlural":"false","existActions":"true","object":"invoice"},"name":"Approve Invoice","id":"approveInvoice","type":"userTask","actions":{"predPoS":"VB","objW":"invoice","predL":"approve","objL":"invoice","objMSD":"pos=noun|type=common|num=singular","predW":"approve","predF":"approve","objF":"invoice","predMSD":"pos=verb|vform=infinitive","objPoS":"NN"},"lane":null,"finalSentence":"The invoice is approved."},"StartEvent_1":{"next":[{"name":null,"id":"assignApprover"}],"finalPhrase":{"objectDeterminant":"true","subject":null,"interrogative":"false","verb":"invoice","complement":null,"objectPlural":"false","existActions":"true","object":"received"},"name":"Invoice received","id":"StartEvent_1","type":"startEvent","actions":{"predPoS":"NN","objW":"received","predL":"invoice","objL":"receive","objMSD":"pos=verb|vform=past","predW":"invoice","predF":"invoice","objF":"received","predMSD":"pos=noun|type=common|num=singular","objPoS":"VBD"},"lane":null,"finalSentence":"The received is invoiced."},"archiveInvoice":{"next":[{"name":null,"id":"invoiceProcessed"}],"finalPhrase":{"objectDeterminant":"true","subject":null,"interrogative":"false","verb":"archive","complement":null,"objectPlural":"false","existActions":"true","object":"invoice"},"name":"Archive Invoice","id":"archiveInvoice","type":"serviceTask","actions":{"predPoS":"NN","objW":"invoice","predL":"archive","objL":"invoice","objMSD":"pos=noun|type=common|num=singular","predW":"archive","predF":"archive","objF":"invoice","predMSD":"pos=noun|type=common|num=singular","objPoS":"NN"},"lane":null,"finalSentence":"The invoice is archived."},"reviewInvoice":{"next":[{"name":null,"id":"reviewSuccessful_gw"}],"finalPhrase":{"objectDeterminant":"false","subject":null,"interrogative":"false","verb":null,"complement":null,"objectPlural":"false","existActions":"false","object":null},"name":"Rechnung klären","id":"reviewInvoice","type":"userTask","actions":null,"lane":null,"finalSentence":"Rechnung klären."},"assignApprover":{"next":[{"name":null,"id":"approveInvoice"}],"finalPhrase":{"objectDeterminant":"false","subject":null,"interrogative":"false","verb":"assign","complement":null,"objectPlural":"false","existActions":"true","object":null},"name":"Assign Approver","id":"assignApprover","type":"userTask","actions":{"otherL":"approver","predPoS":"VB","predL":"assign","otherPoS":"RB","predW":"assign","predF":"assign","otherW":"approver","otherF":"approver","predMSD":"pos=verb|vform=infinitive","otherMSD":"pos=adverb|type=general"},"lane":null,"finalSentence":"Is assigned."},"invoiceNotProcessed":{"next":[],"finalPhrase":{"objectDeterminant":"false","subject":null,"interrogative":"false","verb":null,"complement":null,"objectPlural":"false","existActions":"false","object":null},"name":"Invoice not processed","id":"invoiceNotProcessed","type":"endEvent","actions":null,"lane":null,"finalSentence":"Invoice not processed."},"reviewSuccessful_gw":{"next":[{"name":"yes","id":"approveInvoice"},{"name":"no","id":"invoiceNotProcessed"}],"finalPhrase":{"objectDeterminant":"true","subject":null,"interrogative":"true","verb":"review","complement":null,"objectPlural":"false","existActions":"true","object":"successful"},"name":"Review successful?","id":"reviewSuccessful_gw","type":"exclusiveGateway","actions":{"predPoS":"NN","objW":"successful","predL":"review","objL":"successful","objMSD":"pos=adjective","predW":"review","predF":"review","objF":"successful","predMSD":"pos=noun|type=common|num=singular","objPoS":"JJ"},"lane":null,"finalSentence":"Does review the successful?"},"prepareBankTransfer":{"next":[{"name":null,"id":"archiveInvoice"}],"finalPhrase":{"objectDeterminant":"true","subject":null,"interrogative":"false","verb":"prepare","complement":null,"objectPlural":"false","existActions":"true","object":"bank transfer"},"name":"Prepare  Bank  Transfer","id":"prepareBankTransfer","type":"userTask","actions":{"predPoS":"VB","objW":"bank transfer","predL":"prepare","objL":"transfer","objMSD":"pos=noun|type=common|num=singular","predW":"prepare","predF":"prepare","objF":"transfer","predMSD":"pos=verb|vform=infinitive","objPoS":"NN"},"lane":null,"finalSentence":"The bank transfer is prepared."},"invoiceProcessed":{"next":[],"finalPhrase":{"objectDeterminant":"true","subject":null,"interrogative":"false","verb":"invoice","complement":null,"objectPlural":"false","existActions":"true","object":"processed"},"name":"Invoice processed","id":"invoiceProcessed","type":"endEvent","actions":{"predPoS":"NN","objW":"processed","predL":"invoice","objL":"process","objMSD":"pos=verb|vform=participle","predW":"invoice","predF":"invoice","objF":"processed","predMSD":"pos=noun|type=common|num=singular","objPoS":"VBN"},"lane":null,"finalSentence":"The processed is invoiced."}}